ash_kms/__init__.py
ash_kms/encryption_service.py
ash_kms/exceptions.py
ash_kms-0.1.1.dist-info/METADATA
ash_kms-0.1.1.dist-info/WHEEL
ash_kms-0.1.1.dist-info/RECORD
