Metadata-Version: 2.1
Name: ash-kms
Version: 0.1.1
Summary: 
Author: Raman Shakun
Author-email: shakunroman@gmail.com
Requires-Python: >=3.11,<4.0
Classifier: Programming Language :: Python :: 3
Classifier: Programming Language :: Python :: 3.11
Requires-Dist: crcmod (>=1.7,<2.0)
Requires-Dist: google-cloud-kms (>=2.19.1,<3.0.0)
Requires-Dist: six (>=1.16.0,<2.0.0)
